README.md
setup.py
onnds/__init__.py
onnds/ds.py
onnds.egg-info/PKG-INFO
onnds.egg-info/SOURCES.txt
onnds.egg-info/dependency_links.txt
onnds.egg-info/requires.txt
onnds.egg-info/top_level.txt
onnds/libs/__init__.py
onnds/libs/db.py
onnds/libs/legacy.py