Metadata-Version: 2.1
Name: onnds
Version: 0.0.14
Summary: Convenience module for interacting with Trend Micro Deep Security
Home-page: http://oznetnerd.com
Author: Will Robinson
Author-email: will@oznetnerd.com
License: UNKNOWN
Platform: UNKNOWN
